{"stats":{"minecraft:broken":{"minecraft:stone_pickaxe":7,"minecraft:stone_axe":2,"minecraft:iron_pickaxe":1,"minecraft:stone_shovel":7},"minecraft:mined":{"minecraft:oak_sapling":7,"minecraft:oak_door":1,"minecraft:cherry_log":3,"minecraft:glow_lichen":2,"minecraft:granite":195,"minecraft:grass_block":890,"minecraft:furnace":3,"minecraft:iron_ore":34,"minecraft:andesite":161,"minecraft:deepslate_iron_ore":3,"minecraft:dirt_path":1,"minecraft:lantern":1,"minecraft:stripped_oak_log":13,"minecraft:stone":651,"minecraft:cherry_stairs":23,"minecraft:glass_pane":2,"minecraft:cherry_planks":4,"minecraft:oak_fence":2,"minecraft:crafting_table":5,"minecraft:torch":2,"minecraft:copper_ore":20,"minecraft:tall_grass":8,"minecraft:cobblestone":11,"minecraft:oak_planks":202,"minecraft:diorite":76,"minecraft:wall_torch":4,"minecraft:grass":31,"minecraft:oak_log":16,"minecraft:coal_ore":37,"minecraft:cherry_leaves":53,"minecraft:gravel":4,"minecraft:sand":59,"minecraft:dirt":63,"minecraft:cobweb":24,"minecraft:oak_leaves":170,"minecraft:deepslate":10},"minecraft:crafted":{"minecraft:cherry_planks":368,"minecraft:oak_door":3,"minecraft:oak_planks":724,"minecraft:stone_shovel":9,"minecraft:fishing_rod":1,"minecraft:iron_nugget":207,"minecraft:furnace":3,"minecraft:cooked_mutton":1,"minecraft:glass_pane":144,"minecraft:glass":58,"minecraft:cherry_trapdoor":20,"minecraft:lantern":25,"minecraft:iron_boots":1,"minecraft:cherry_stairs":80,"minecraft:stone_pickaxe":9,"minecraft:chest":4,"minecraft:oak_fence":78,"minecraft:cooked_porkchop":4,"minecraft:crafting_table":5,"minecraft:iron_helmet":1,"minecraft:iron_sword":1,"minecraft:bucket":2,"minecraft:stone_axe":6,"minecraft:air":0,"minecraft:iron_chestplate":1,"minecraft:charcoal":15,"minecraft:shield":1,"minecraft:stick":148,"minecraft:iron_ingot":32,"minecraft:iron_pickaxe":2,"minecraft:iron_block":3,"minecraft:iron_leggings":1,"minecraft:anvil":1,"minecraft:torch":84,"minecraft:shears":1},"minecraft:custom":{"minecraft:interact_with_anvil":2,"minecraft:mob_kills":26,"minecraft:interact_with_crafting_table":61,"minecraft:eat_cake_slice":3,"minecraft:time_since_death":19958,"minecraft:sprint_one_cm":503600,"minecraft:walk_one_cm":819218,"minecraft:damage_blocked_by_shield":45,"minecraft:drop":16,"minecraft:talked_to_villager":10,"minecraft:play_time":228000,"minecraft:deaths":10,"minecraft:sneak_time":12722,"minecraft:walk_under_water_one_cm":51535,"minecraft:jump":2897,"minecraft:walk_on_water_one_cm":38436,"minecraft:total_world_time":228000,"minecraft:interact_with_furnace":63,"minecraft:time_since_rest":19985,"minecraft:damage_taken":3236,"minecraft:damage_absorbed":40,"minecraft:damage_dealt":4260,"minecraft:swim_one_cm":144482,"minecraft:fly_one_cm":561189,"minecraft:player_kills":2,"minecraft:open_chest":99,"minecraft:crouch_one_cm":56957,"minecraft:fall_one_cm":68119},"minecraft:picked_up":{"minecraft:crafting_table":6,"minecraft:suspicious_stew":1,"minecraft:wooden_pickaxe":1,"minecraft:string":25,"minecraft:raw_copper":78,"minecraft:diamond_leggings":1,"minecraft:cobbled_deepslate":9,"minecraft:furnace":3,"minecraft:stick":228,"minecraft:raw_iron":35,"minecraft:cherry_stairs":23,"minecraft:oak_door":2,"minecraft:oak_fence":2,"minecraft:torch":8,"minecraft:bowl":1,"minecraft:cherry_log":185,"minecraft:diorite":77,"minecraft:carrot":5,"minecraft:rotten_flesh":12,"minecraft:stone_sword":1,"minecraft:arrow":4,"minecraft:mutton":1,"minecraft:white_wool":1,"minecraft:cobblestone":653,"minecraft:stripped_oak_log":13,"minecraft:cherry_planks":4,"minecraft:cherry_leaves":48,"minecraft:glow_ink_sac":3,"minecraft:salmon":8,"minecraft:andesite":164,"minecraft:oak_log":277,"minecraft:lapis_lazuli":3,"minecraft:paper":9,"minecraft:dirt":953,"minecraft:lantern":1,"minecraft:bone":6,"minecraft:apple":13,"minecraft:wheat_seeds":25,"minecraft:oak_planks":274,"minecraft:gravel":4,"minecraft:sand":58,"minecraft:granite":196,"minecraft:cherry_sapling":84,"minecraft:golden_apple":6,"minecraft:emerald":7,"minecraft:oak_sapling":176,"minecraft:coal":69,"minecraft:oak_leaves":150},"minecraft:killed_by":{"minecraft:player":1,"minecraft:skeleton":6,"minecraft:zombie":2},"minecraft:dropped":{"minecraft:crafting_table":1,"minecraft:diamond_leggings":1,"minecraft:apple":1,"minecraft:coal":32,"minecraft:stick":89,"minecraft:emerald":7,"minecraft:string":2,"minecraft:stone_sword":1,"minecraft:bowl":2,"minecraft:rotten_flesh":2,"minecraft:oak_planks":93,"minecraft:carrot":5,"minecraft:oak_sapling":40},"minecraft:used":{"minecraft:oak_fence":60,"minecraft:cherry_sapling":6,"minecraft:stone_shovel":1011,"minecraft:chest":4,"minecraft:shield":1,"minecraft:iron_sword":50,"minecraft:rotten_flesh":3,"minecraft:oak_door":4,"minecraft:torch":64,"minecraft:dirt":116,"minecraft:anvil":1,"minecraft:salmon_bucket":1,"minecraft:granite":95,"minecraft:lava_bucket":5,"minecraft:lantern":26,"minecraft:cherry_trapdoor":6,"minecraft:cherry_leaves":4,"minecraft:furnace":7,"minecraft:oak_sapling":89,"minecraft:cherry_log":2,"minecraft:cooked_mutton":1,"minecraft:water_bucket":2,"minecraft:diorite":20,"minecraft:stone_pickaxe":984,"minecraft:oak_planks":475,"minecraft:cherry_planks":11,"minecraft:oak_leaves":47,"minecraft:cookie":6,"minecraft:golden_apple":3,"minecraft:crafting_table":10,"minecraft:blast_furnace":1,"minecraft:shears":211,"minecraft:oak_log":74,"minecraft:apple":26,"minecraft:suspicious_stew":1,"minecraft:iron_pickaxe":226,"minecraft:stone_axe":389,"minecraft:fishing_rod":1,"minecraft:cobblestone":554,"minecraft:cherry_stairs":32,"minecraft:cooked_porkchop":4,"minecraft:andesite":143,"minecraft:bucket":9,"minecraft:glass_pane":130,"minecraft:stripped_oak_log":1},"minecraft:killed":{"minecraft:cave_spider":1,"minecraft:spider":1,"minecraft:skeleton":5,"minecraft:salmon":8,"minecraft:creeper":1,"minecraft:sheep":1,"minecraft:zombie":9}},"DataVersion":3465}